MANIFEST.in
README.md
setup.cfg
setup.py
src/nessus/__init__.py
src/pynessusrpc.egg-info/PKG-INFO
src/pynessusrpc.egg-info/SOURCES.txt
src/pynessusrpc.egg-info/dependency_links.txt
src/pynessusrpc.egg-info/not-zip-safe
src/pynessusrpc.egg-info/top_level.txt