Metadata-Version: 1.0
Name: pynessusrpc
Version: 0.3
Summary: Python Nessus RPC client.
Home-page: UNKNOWN
Author: Nadeem Douba
Author-email: ndouba@gmail.com
License: GPL
Platform: UNKNOWN
